docker_odoo_env/__init__.py
docker_odoo_env/command_line.py
docker_odoo_env/config.py
docker_odoo_env/messages.py
docker_odoo_env/parse_args.py
docker_odoo_env/test_oe.py
docker_odoo_env/commands/__init__.py
docker_odoo_env/commands/backup_command.py
docker_odoo_env/commands/command.py
docker_odoo_env/commands/config_command.py
docker_odoo_env/commands/docker_down_command.py
docker_odoo_env/commands/docker_up_command.py
docker_odoo_env/commands/odoo_conf_command.py
docker_odoo_env/commands/pull_command.py
docker_odoo_env/commands/update_all.py
docker_odoo_env/commands/update_command.py
docker_odoo_env/commands/upgrade_command.py
docker_odoo_env-0.0a10.dist-info/LICENSE
docker_odoo_env-0.0a10.dist-info/METADATA
docker_odoo_env-0.0a10.dist-info/WHEEL
docker_odoo_env-0.0a10.dist-info/entry_points.txt
docker_odoo_env-0.0a10.dist-info/top_level.txt
docker_odoo_env-0.0a10.dist-info/RECORD
