Metadata-Version: 2.1
Name: docker-odoo-env
Version: 0.0a10
Summary: A small tool to manage Dockerized Odoo
Home-page: https://github.com/jobiols/docker_odoo_env
Author: jeo Software
Author-email: jorge.obiols@gmail.com
License: UNKNOWN
Keywords: odoo docker environment
Platform: UNKNOWN
Classifier: Development Status :: 1 - Planning
Classifier: Intended Audience :: Developers
Classifier: License :: OSI Approved :: MIT License
Classifier: Programming Language :: Python :: 2.7
Classifier: Programming Language :: Python :: 3.4
Classifier: Programming Language :: Python :: 3.5
Classifier: Programming Language :: Python :: 3.6
Classifier: Operating System :: OS Independent
Classifier: Topic :: Software Development :: Testing :: Unit
Classifier: Topic :: System :: Software Distribution
Requires-Dist: pyyaml
